client/__init__.py
client/api.py
client/config.py
client/console.py
client/signals.py
client/utils.py
matillioncli-1.0.4.dist-info/LICENSE
matillioncli-1.0.4.dist-info/METADATA
matillioncli-1.0.4.dist-info/WHEEL
matillioncli-1.0.4.dist-info/entry_points.txt
matillioncli-1.0.4.dist-info/top_level.txt
matillioncli-1.0.4.dist-info/RECORD
