Metadata-Version: 2.1
Name: matillioncli
Version: 1.0.4
Summary: A cli tool for running Matillion jobs
Home-page: https://github.com/Rouhija/matillion-cli
Author: Sami Rouhe
Author-email: rouhesami@gmail.com
License: UNKNOWN
Platform: UNKNOWN
Classifier: Programming Language :: Python :: 3
Classifier: License :: OSI Approved :: MIT License
Classifier: Operating System :: OS Independent
Requires-Dist: requests
